weixin_client_python.cpython-38-x86_64-linux-gnu.so
wxchat-0.1.4.dist-info/WHEEL
wxchat-0.1.4.dist-info/top_level.txt
wxchat-0.1.4.dist-info/RECORD
wxchat-0.1.4.dist-info/METADATA
wxchat/__init__.py
wxchat/logger.py
wxchat/weixin.py
wxchat.libs/libgcc_s-a04fdf82.so.1
wxchat.libs/libstdc++-a9383cce.so.6.0.28
